MANIFEST.in
README.md
setup.py
src/nymp/__init__.py
src/nymp/config.py
src/nymp/defaults.py
src/nymp/events.py
src/nymp/start.py
src/nymp.egg-info/PKG-INFO
src/nymp.egg-info/SOURCES.txt
src/nymp.egg-info/dependency_links.txt
src/nymp.egg-info/entry_points.txt
src/nymp.egg-info/top_level.txt
src/nymp/gui/__init__.py
src/nymp/gui/base.py
src/nymp/gui/browser.py
src/nymp/gui/buffer.py
src/nymp/gui/current.py
src/nymp/gui/loop.py
src/nymp/gui/playlist.py
src/nymp/gui/status.py
src/nymp/gui/widgets.py
src/nymp/xmms/__init__.py
src/nymp/xmms/connection.py
src/nymp/xmms/helper.py
src/nymp/xmms/player.py
src/nymp/xmms/playlist.py