Metadata-Version: 1.1
Name: nymp
Version: 0.0.2
Summary: A graphical xmms2 cli frontend. It is library focused and provides a tree view on your collection
Home-page: http://www.chaossource.net/nymp/
Author: Thammi
Author-email: thammi@chaossource.net
License: GPLv3
Keywords: xmms2 audio cli
Platform: UNKNOWN
Classifier: Programming Language :: Python :: 2
Classifier: Development Status :: 4 - Beta
Classifier: Topic :: Multimedia :: Sound/Audio
Classifier: License :: OSI Approved :: GNU General Public License (GPL)
Classifier: Environment :: Console
